bpe_qwen-0.1.5.dist-info/METADATA
bpe_qwen-0.1.5.dist-info/WHEEL
bpe_qwen-0.1.5.dist-info/licenses/LICENSE
bpe_qwen/__init__.py
bpe_qwen/__init__.pyi
bpe_qwen/auto_linear_tokenizer.py
bpe_qwen/bpe_qwen.cpython-311-aarch64-linux-gnu.so
bpe_qwen/hf_patch.py
bpe_qwen-0.1.5.dist-info/RECORD
