Metadata-Version: 2.4
Name: bpe-qwen
Version: 0.1.5
Classifier: Programming Language :: Rust
Classifier: Programming Language :: Python :: Implementation :: CPython
Classifier: Programming Language :: Python :: Implementation :: PyPy
Classifier: Programming Language :: Python :: 3
Classifier: Programming Language :: Python :: 3.10
Classifier: Programming Language :: Python :: 3.11
Classifier: Programming Language :: Python :: 3.12
Requires-Dist: pytest ; extra == 'tests'
Requires-Dist: transformers ; extra == 'dev'
Requires-Dist: datasets ; extra == 'dev'
Requires-Dist: huggingface-hub ; extra == 'dev'
Provides-Extra: tests
Provides-Extra: dev
License-File: LICENSE
Summary: A blazing-fast BPE tokenizer for Qwen models, built with Rust. Achieves 6x faster tokenization with parallelism compared to HuggingFace tokenizers.
Requires-Python: >=3.10, <3.13
